Metadata-Version: 2.4
Name: llama-index-readers-semanticscholar
Version: 0.4.1
Summary: llama-index readers semanticscholar integration
Author-email: Your Name <you@example.com>
Maintainer: shauryr
License-Expression: MIT
License-File: LICENSE
Keywords: paper,research,scholar,semantic
Requires-Python: <4.0,>=3.9
Requires-Dist: arxiv==1.4.8
Requires-Dist: llama-index-core<0.15,>=0.13.0
Requires-Dist: pypdf2==3.0.1
Requires-Dist: semanticscholar==0.4.1
